odoo/addons/web_apply_field_style/README.rst
odoo/addons/web_apply_field_style/__init__.py
odoo/addons/web_apply_field_style/__manifest__.py
odoo/addons/web_apply_field_style/demo/__init__.py
odoo/addons/web_apply_field_style/demo/base.py
odoo/addons/web_apply_field_style/i18n/es.po
odoo/addons/web_apply_field_style/i18n/it.po
odoo/addons/web_apply_field_style/i18n/web_apply_field_style.pot
odoo/addons/web_apply_field_style/models/__init__.py
odoo/addons/web_apply_field_style/models/base.py
odoo/addons/web_apply_field_style/readme/CONFIGURE.rst
odoo/addons/web_apply_field_style/readme/CONTRIBUTORS.rst
odoo/addons/web_apply_field_style/readme/DESCRIPTION.rst
odoo/addons/web_apply_field_style/static/description/demo.png
odoo/addons/web_apply_field_style/static/description/icon.png
odoo/addons/web_apply_field_style/static/description/index.html
odoo/addons/web_apply_field_style/tests/__init__.py
odoo/addons/web_apply_field_style/tests/test_module.py
odoo_addon_web_apply_field_style-16.0.1.0.1.4.dist-info/METADATA
odoo_addon_web_apply_field_style-16.0.1.0.1.4.dist-info/WHEEL
odoo_addon_web_apply_field_style-16.0.1.0.1.4.dist-info/top_level.txt
odoo_addon_web_apply_field_style-16.0.1.0.1.4.dist-info/RECORD
